pyBeastx/__init__.py
pyBeastx/__main__.py
pyBeastx/configs.py
pyBeastx/version.py
pyBeastx/dB/__init__.py
pyBeastx/dB/_core.py
pyBeastx/dB/afk_db.py
pyBeastx/dB/antiflood_db.py
pyBeastx/dB/asst_fns.py
pyBeastx/dB/asstcmd_db.py
pyBeastx/dB/blacklist_chat_db.py
pyBeastx/dB/blacklist_db.py
pyBeastx/dB/botchat_db.py
pyBeastx/dB/broadcast_db.py
pyBeastx/dB/ch_db.py
pyBeastx/dB/chatBot_db.py
pyBeastx/dB/clean_db.py
pyBeastx/dB/echo_db.py
pyBeastx/dB/filter_db.py
pyBeastx/dB/forcesub_db.py
pyBeastx/dB/gban_mute_db.py
pyBeastx/dB/gcast_blacklist_db.py
pyBeastx/dB/greetings_db.py
pyBeastx/dB/logusers_db.py
pyBeastx/dB/mute_db.py
pyBeastx/dB/night_db.py
pyBeastx/dB/notes_db.py
pyBeastx/dB/nsfw_db.py
pyBeastx/dB/pmpermit_db.py
pyBeastx/dB/snips_db.py
pyBeastx/dB/sudos.py
pyBeastx/dB/username_db.py
pyBeastx/dB/vc_group.py
pyBeastx/dB/vc_sudos.py
pyBeastx/dB/warn_db.py
pyBeastx/functions/FastTelethon.py
pyBeastx/functions/__init__.py
pyBeastx/functions/admins.py
pyBeastx/functions/gdrive.py
pyBeastx/functions/google_image.py
pyBeastx/functions/helper.py
pyBeastx/functions/info.py
pyBeastx/functions/misc.py
pyBeastx/functions/tools.py
pyBeastx/functions/ytdl.py
pyBeastx/misc/__init__.py
pyBeastx/misc/_assistant.py
pyBeastx/misc/_decorators.py
pyBeastx/misc/_supporter.py
pyBeastx/misc/_wrappers.py
pyBeastx/startup/BaseClient.py
pyBeastx/startup/__init__.py
pyBeastx/startup/connections.py
pyBeastx/startup/exceptions.py
pyBeastx/startup/funcs.py
pyBeastx/startup/loader.py
pyBeastx/startup/utils.py
pybeastx-2021.10.11.4.dist-info/LICENSE
pybeastx-2021.10.11.4.dist-info/METADATA
pybeastx-2021.10.11.4.dist-info/WHEEL
pybeastx-2021.10.11.4.dist-info/top_level.txt
pybeastx-2021.10.11.4.dist-info/RECORD
