Metadata-Version: 2.1
Name: pybeastx
Version: 2021.10.11.4
Summary: A Secure and Powerful Python-Telethon Based Library For Ultroid Userbot.
Home-page: https://github.com/msy1717/Beast-X
Author: msy1717
Author-email: mrunalgaming7@gmail.com
License: GNU AFFERO GENERAL PUBLIC LICENSE (v3)
Project-URL: Bug Tracker, https://github.com/msy1717/Beast-X/issues
Project-URL: Documentation, https://github.com/msy1717/Beast-X
Project-URL: Source Code, https://github.com/msy1717/Beast-X
Platform: UNKNOWN
Classifier: Programming Language :: Python :: 3
Classifier: Programming Language :: Python :: 3.6
Classifier: Programming Language :: Python :: 3.7
Classifier: Programming Language :: Python :: 3.8
Classifier: Programming Language :: Python :: 3.9
Classifier: License :: OSI Approved :: GNU General Public License v3 (GPLv3)
Classifier: Operating System :: OS Independent
Requires-Python: >=3.6
Requires-Dist: redis
Requires-Dist: python-decouple (==3.3)
Requires-Dist: python-dotenv (==0.15.0)
Requires-Dist: aiofiles
Requires-Dist: aiohttp
Requires-Dist: safety
